{
  "groups": [
    {
      "name": "Malachowsky Hall",
      "counts": {
        "Online": 206,
        "Offline": 51
      },
      "total": 257,
      "onlinePct": 80.2
    },
    {
      "name": "Scheduling Panels",
      "counts": {
        "Online": 1
      },
      "total": 1,
      "onlinePct": 100.0
    },
    {
      "name": "UF Libraries",
      "counts": {
        "Online": 24
      },
      "total": 24,
      "onlinePct": 100.0
    },
    {
      "name": "UFIT AV Install Group",
      "counts": {
        "Online": 122,
        "Offline": 45
      },
      "total": 167,
      "onlinePct": 73.1
    },
    {
      "name": "UFIT Conference Rooms",
      "counts": {
        "Online": 79,
        "Offline": 16
      },
      "total": 95,
      "onlinePct": 83.2
    },
    {
      "name": "UFIT Learning Spaces",
      "counts": {
        "Online": 416,
        "Offline": 24
      },
      "total": 440,
      "onlinePct": 94.5
    }
  ],
  "meta": {
    "generatedAtUtc": "2025-12-10T12:33:21.501029+00:00",
    "groupCount": 6
  }
}