{
  "groups": [
    {
      "name": "Malachowsky Hall",
      "counts": {
        "Online": 204,
        "Offline": 53
      },
      "total": 257,
      "onlinePct": 79.4
    },
    {
      "name": "Scheduling Panels",
      "counts": {
        "Offline": 1
      },
      "total": 1,
      "onlinePct": 0.0
    },
    {
      "name": "UF Libraries",
      "counts": {
        "Online": 24
      },
      "total": 24,
      "onlinePct": 100.0
    },
    {
      "name": "UFIT AV Install Group",
      "counts": {
        "Online": 120,
        "Offline": 47
      },
      "total": 167,
      "onlinePct": 71.9
    },
    {
      "name": "UFIT Conference Rooms",
      "counts": {
        "Online": 88,
        "Offline": 7
      },
      "total": 95,
      "onlinePct": 92.6
    },
    {
      "name": "UFIT Learning Spaces",
      "counts": {
        "Online": 414,
        "Offline": 29
      },
      "total": 443,
      "onlinePct": 93.5
    }
  ],
  "meta": {
    "generatedAtUtc": "2025-12-02T14:32:38.790252+00:00",
    "groupCount": 6
  }
}